LICENSE
README.md
setup.py
vncx/__init__.py
vncx/client.py
vncx/protocol.py
vncx.egg-info/PKG-INFO
vncx.egg-info/SOURCES.txt
vncx.egg-info/dependency_links.txt
vncx.egg-info/requires.txt
vncx.egg-info/top_level.txt